plinder/__init__.py
plinder/_version.py
plinder/core/__init__.py
plinder/core/index/__init__.py
plinder/core/index/system.py
plinder/core/index/utils.py
plinder/core/loader/__init__.py
plinder/core/loader/dataset.py
plinder/core/loader/featurizer.py
plinder/core/loader/transforms.py
plinder/core/loader/utils.py
plinder/core/scores/__init__.py
plinder/core/scores/clusters.py
plinder/core/scores/index.py
plinder/core/scores/ligand.py
plinder/core/scores/links.py
plinder/core/scores/protein.py
plinder/core/scores/query.py
plinder/core/split/__init__.py
plinder/core/split/plot.py
plinder/core/split/utils.py
plinder/core/structure/__init__.py
plinder/core/structure/atoms.py
plinder/core/structure/contacts.py
plinder/core/structure/diffdock_utils.py
plinder/core/structure/models.py
plinder/core/structure/smallmols_similarity.py
plinder/core/structure/smallmols_utils.py
plinder/core/structure/structure.py
plinder/core/structure/superimpose.py
plinder/core/structure/surgery.py
plinder/core/structure/vendored.py
plinder/core/utils/__init__.py
plinder/core/utils/config.py
plinder/core/utils/constants.py
plinder/core/utils/cpl.py
plinder/core/utils/dataclass.py
plinder/core/utils/dec.py
plinder/core/utils/gcs.py
plinder/core/utils/io.py
plinder/core/utils/load_systems.py
plinder/core/utils/log.py
plinder/core/utils/schemas.py
plinder/core/utils/unpack.py
plinder/data/__init__.py
plinder/data/_version.py
plinder/data/clusters.py
plinder/data/databases.py
plinder/data/docs.py
plinder/data/final_structure_qc.py
plinder/data/get_system_annotations.py
plinder/data/leakage.py
plinder/data/save_linked_structures.py
plinder/data/splits.py
plinder/data/column_descriptions/__init__.py
plinder/data/column_descriptions/entry.tsv
plinder/data/column_descriptions/entry_validation.tsv
plinder/data/column_descriptions/extra.tsv
plinder/data/column_descriptions/ligand_interacting_ligand_chains.tsv
plinder/data/column_descriptions/ligand_interacting_ligand_chains_validation.tsv
plinder-0.2.25.dist-info/LICENSE.txt
plinder-0.2.25.dist-info/METADATA
plinder-0.2.25.dist-info/WHEEL
plinder-0.2.25.dist-info/entry_points.txt
plinder-0.2.25.dist-info/top_level.txt
plinder-0.2.25.dist-info/RECORD
