Metadata-Version: 2.1
Name: plinder
Version: 0.2.25
Summary: PLINDER: The Protein-Ligand INteraction Dataset and Evaluation Resource
Project-URL: Homepage, https://github.com/plinder-org/plinder
Project-URL: Issues, https://github.com/plinder-org/plinder/issues
Classifier: Programming Language :: Python :: 3
Classifier: License :: OSI Approved :: Apache Software License
Classifier: Operating System :: OS Independent
Requires-Python: >=3.10
License-File: LICENSE.txt
Requires-Dist: biotite>=1.0
Requires-Dist: numpy<2
Requires-Dist: pandas
Requires-Dist: typing-extensions
Requires-Dist: pydantic
Requires-Dist: tqdm
Requires-Dist: plotly
Requires-Dist: nbformat
Requires-Dist: google-cloud-storage
Requires-Dist: gcsfs
Requires-Dist: gemmi
Requires-Dist: rdkit>=2024.03.6
Requires-Dist: pyarrow
Requires-Dist: omegaconf
Requires-Dist: mmcif
Requires-Dist: eval-type-backport
Requires-Dist: posebusters
Requires-Dist: duckdb
Requires-Dist: cloudpathlib
Requires-Dist: mols2grid
Requires-Dist: six
Provides-Extra: dev
Requires-Dist: plinder[lint,test,type]; extra == "dev"
Provides-Extra: docs
Requires-Dist: itables; extra == "docs"
Requires-Dist: jupyter-sphinx; extra == "docs"
Requires-Dist: jupyterlab-myst; extra == "docs"
Requires-Dist: jupytext; extra == "docs"
Requires-Dist: myst-nb; extra == "docs"
Requires-Dist: myst-parser[linkify]; extra == "docs"
Requires-Dist: numpydoc; extra == "docs"
Requires-Dist: pydata-sphinx-theme==0.15.4; extra == "docs"
Requires-Dist: sphinx; extra == "docs"
Requires-Dist: sphinx-copybutton; extra == "docs"
Requires-Dist: sphinx-design; extra == "docs"
Requires-Dist: sphinx-gallery; extra == "docs"
Requires-Dist: mols2grid; extra == "docs"
Requires-Dist: matplotlib; extra == "docs"
Provides-Extra: lint
Requires-Dist: ruff==0.1.2; extra == "lint"
Requires-Dist: pre-commit==2.21.0; extra == "lint"
Provides-Extra: loader
Requires-Dist: torch; extra == "loader"
Provides-Extra: plots
Requires-Dist: matplotlib; extra == "plots"
Requires-Dist: seaborn; extra == "plots"
Requires-Dist: mols2grid; extra == "plots"
Requires-Dist: matplotlib-venn; extra == "plots"
Requires-Dist: scipy; extra == "plots"
Provides-Extra: test
Requires-Dist: tox>=4; extra == "test"
Requires-Dist: pytest==7.2.0; extra == "test"
Requires-Dist: pytest-cov==4.0.0; extra == "test"
Requires-Dist: pytest-xdist==3.6.1; extra == "test"
Requires-Dist: build==0.9.0; extra == "test"
Requires-Dist: setuptools-scm[toml]==7.0.5; extra == "test"
Provides-Extra: type
Requires-Dist: mypy==1.2.0; extra == "type"
Requires-Dist: types-PyYAML; extra == "type"
Requires-Dist: types-requests; extra == "type"
